setup.py
model2/__init__.py
model2/base_action.py
model2/test.py
model2/validators.json
model2.egg-info/PKG-INFO
model2.egg-info/SOURCES.txt
model2.egg-info/dependency_links.txt
model2.egg-info/requires.txt
model2.egg-info/top_level.txt
model2/conf/__init__.py
model2/conf/api/__init__.py
model2/conf/api/role.json
model2/conf/api/user.json
model2/role/__init__.py
model2/role/action.py
model2/role/main.py
model2/role/model.py
model2/user/__init__.py
model2/user/action.py
model2/user/main.py
model2/user/model.py