Metadata-Version: 1.0
Name: model2
Version: 1.0.4.7
Summary: model2 sdk
Home-page: UNKNOWN
Author: skyeye
Author-email: skyeye@gmail.com
License: MIT Licence
Keywords: model2,xxx
Platform: any
